envconfig/__init__.py
envconfig/lib.py
pyenvconfig-0.1.0.dist-info/LICENSE
pyenvconfig-0.1.0.dist-info/METADATA
pyenvconfig-0.1.0.dist-info/WHEEL
pyenvconfig-0.1.0.dist-info/top_level.txt
pyenvconfig-0.1.0.dist-info/RECORD
