Metadata-Version: 2.1
Name: pyenvconfig
Version: 0.1.0
Summary: Simple environment variable configuration for Python
Home-page: https://github.com/makramkd/envconfig
Author: Makram Kamaleddine
License: UNKNOWN
Keywords: environment-variables env-var configuration
Platform: UNKNOWN
Classifier: Intended Audience :: Developers
Classifier: Programming Language :: Python :: 3
